mysql_database/__init__.py
mysql_database/database.py
mysql_database/db_connector.py
mysql_database-0.1.12.dist-info/licenses/LICENCE
mysql_database-0.1.12.dist-info/METADATA
mysql_database-0.1.12.dist-info/WHEEL
mysql_database-0.1.12.dist-info/top_level.txt
mysql_database-0.1.12.dist-info/RECORD
