Metadata-Version: 2.4
Name: mysql-database
Version: 0.1.12
Summary: easy calls to mysql databases
Home-page: https://github.com/Ms-Shoshany/mysql-database
Author: hanna
Author-email: channashosh@gmail.com
Classifier: Programming Language :: Python :: 3
Classifier: License :: OSI Approved :: MIT License
Classifier: Operating System :: OS Independent
Requires-Python: >=3.7
License-File: LICENCE
Requires-Dist: mysql-connector-python
Dynamic: author
Dynamic: author-email
Dynamic: classifier
Dynamic: description
Dynamic: description-content-type
Dynamic: home-page
Dynamic: license-file
Dynamic: requires-dist
Dynamic: requires-python
Dynamic: summary
